handpymake/__init__.py
handpymake/main.py
handpymake/process.py
handpymake/test.py
HandPyMake-0.3.dist-info/METADATA
HandPyMake-0.3.dist-info/WHEEL
HandPyMake-0.3.dist-info/entry_points.txt
HandPyMake-0.3.dist-info/top_level.txt
HandPyMake-0.3.dist-info/RECORD
